{"cameraMode":{"drawMode":0,"name":"Shaded","section":"Shading Mode"},"sceneLighting":true,"audioPlay":false,"sceneViewState":{"m_AlwaysRefresh":false,"showFog":true,"showSkybox":true,"showFlares":true,"showImageEffects":true,"showParticleSystems":true,"showVisualEffectGraphs":true,"m_FxEnabled":true},"in2DMode":false,"pivot":{"x":14.167348861694336,"y":-63.50014877319336,"z":147.20237731933595},"rotation":{"x":-0.05933035910129547,"y":-0.8729647397994995,"z":0.4715931713581085,"w":-0.10974570363759995},"size":47.52180480957031,"orthographic":false}